telepotpro/__init__.py
telepotpro/api.py
telepotpro/delegate.py
telepotpro/exception.py
telepotpro/filtering.py
telepotpro/hack.py
telepotpro/helper.py
telepotpro/loop.py
telepotpro/namedtuple.py
telepotpro/routing.py
telepotpro/text.py
telepotpro/aio/__init__.py
telepotpro/aio/api.py
telepotpro/aio/delegate.py
telepotpro/aio/hack.py
telepotpro/aio/helper.py
telepotpro/aio/loop.py
telepotpro/aio/routing.py
telepotpro-13.7.dist-info/licenses/LICENSE.md
telepotpro-13.7.dist-info/METADATA
telepotpro-13.7.dist-info/WHEEL
telepotpro-13.7.dist-info/top_level.txt
telepotpro-13.7.dist-info/RECORD
